klbaselearning/__init__.py
klbaselearning/2022/__init__.py
klbaselearning/2022/my-1-丙-城市气温预测-final.py
klbaselearning/2022/my-10-总决赛-CNN-回归.py
klbaselearning/2022/my-11-baseline1-二模型.py
klbaselearning/2022/my-12-Clustering-with-California-House-Prices.py
klbaselearning/2022/my-13-FCM聚类.py
klbaselearning/2022/my-14-K_means-聚类.py
klbaselearning/2022/my-15-preprocessing.py
klbaselearning/2022/my-2-常用命令.py
klbaselearning/2022/my-3-第三轮-用户感知.py
klbaselearning/2022/my-4-丁_LGBM_合并测试集.py
klbaselearning/2022/my-5-突围赛-小区流量预测.py
klbaselearning/2022/my-6-突围赛-SINR预测-特征工程.py
klbaselearning/2022/my-7-心跳信号分类变形_CNN.py
klbaselearning/2022/my-8-心跳信号分类变形_LGBM.py
klbaselearning/2022/my-9-总决赛-baseline1-599-特征输出.py
klbaselearning/2023/__init__.py
klbaselearning/2023/Prophet/Prophet_2-异常值检测_all.py
klbaselearning/2023/Prophet/Prophet_训练.py
klbaselearning/2023/Prophet/__init__.py
klbaselearning/2023/Prophet/模型融合.py
klbaselearning/2023/基站节能策略合理性预测/1.数据合并.py
klbaselearning/2023/基站节能策略合理性预测/2.数据预处理.py
klbaselearning/2023/基站节能策略合理性预测/4.特征优化方法.py
klbaselearning/2023/基站节能策略合理性预测/__init__.py
klbaselearning/2023/基站节能策略合理性预测/合理性预测-训练-F1_A.py
klbaselearning/2023/基站节能策略合理性预测/节能合理性预测-LGBM.py
klbaselearning/2023/基站节能策略合理性预测/节能合理性预测-特征工程-时间序列-Copy1.py
klbaselearning/2023/基站节能策略合理性预测/节能合理性预测-特征工程-时间序列.py
klbaselearning/2023/移网满意度赛道/__init__.py
klbaselearning/2023/移网满意度赛道/移网满意度-CAT.py
klbaselearning/2023/移网满意度赛道/移网满意度-EDA.py
klbaselearning/2023/移网满意度赛道/移网满意度-FE.py
klbaselearning/2023/移网满意度赛道/移网满意度-lgbm.py
klbaselearning/2023/移网满意度赛道/移网满意度-lgbm_1.68064.py
klbaselearning/2023/移网满意度赛道/移网满意度-特征工程-new.py
klbaselearning/2023/移网满意度赛道/移网满意度-特征工程.py
klbaselearning/2023/移网满意度赛道/移网满意度-训练-回归.py
klbaselearning/2023/移网满意度赛道/移网满意度-训练-树模型.py
klbaselearning/2023/移网用户离网预测/__init__.py
klbaselearning/2023/移网用户离网预测/feature_engineering.py
klbaselearning/2023/移网用户离网预测/model_train_9704.py
klbaselearning/2023/移网用户离网预测/model_train_AG.py
klbaselearning/2023/移网用户离网预测/result_predictor.py
klbaselearning/2023/线上商城用户购买倾向预测挑战赛/__init__.py
klbaselearning-0.1.4.dist-info/METADATA
klbaselearning-0.1.4.dist-info/WHEEL
klbaselearning-0.1.4.dist-info/top_level.txt
klbaselearning-0.1.4.dist-info/RECORD
