Metadata-Version: 2.1
Name: klbaselearning
Version: 0.1.4
Summary: A package with machine learning tasks
Home-page: UNKNOWN
Author: kkl
Author-email: kkl2@gmail.com
License: UNKNOWN
Platform: UNKNOWN
Classifier: Programming Language :: Python :: 3
Classifier: License :: OSI Approved :: MIT License
Classifier: Operating System :: OS Independent
Requires-Python: >=3.6
